blocktool/__init__.py
blocktool-0.0.0a1.dist-info/LICENSE
blocktool-0.0.0a1.dist-info/METADATA
blocktool-0.0.0a1.dist-info/WHEEL
blocktool-0.0.0a1.dist-info/top_level.txt
blocktool-0.0.0a1.dist-info/RECORD
